jihad.py
setup.py
xml2jihad
jihad.egg-info/PKG-INFO
jihad.egg-info/SOURCES.txt
jihad.egg-info/dependency_links.txt
jihad.egg-info/requires.txt
jihad.egg-info/top_level.txt