Metadata-Version: 1.0
Name: jihad
Version: 0.2.2
Summary: Use haml and jinja2 in OpenERP views
Home-page: https://github.com/Psycojoker/jihad
Author: Laurent Peuch
Author-email: cortex@worlddomination.be
License: GPLv3+
Platform: UNKNOWN
